<?xml version="1.0"?>
<descriptor xmlns="http://digimend.sourceforge.net" xmlns:xsi="http://www.w3.org/2001/XMLSchema-instance" xsi:schemaLocation="http://digimend.sourceforge.net hidrd.xsd">
  <usage_page>digitizer<!-- Digitizer (0Dh) --></usage_page>
  <usage>digitizer_pen<!-- Pen (02h, application collection) --></usage>
  <COLLECTION type="application">
    <report_id>6</report_id>
    <usage>digitizer_stylus<!-- Stylus (20h, application collection, logical collection) --></usage>
    <COLLECTION type="physical">
      <usage>digitizer_tip_switch<!-- Tip switch (42h, momentary control) --></usage>
      <usage>digitizer_barrel_switch<!-- Barrel switch (44h, momentary control) --></usage>
      <usage>digitizer_eraser<!-- Eraser (45h, momentary control) --></usage>
      <usage>digitizer_invert<!-- Invert (3Ch, momentary control) --></usage>
      <usage>0</usage>
      <usage>digitizer_in_range<!-- In range (32h, momentary control) --></usage>
      <logical_minimum>0</logical_minimum>
      <logical_maximum>1</logical_maximum>
      <report_size>1</report_size>
      <report_count>6</report_count>
      <input>
        <variable/>
      </input>
      <report_count>2</report_count>
      <input>
        <constant/>
        <variable/>
      </input>
      <usage_page>desktop<!-- Generic desktop controls (01h) --></usage_page>
      <usage>desktop_x<!-- X (30h, dynamic value) --></usage>
      <logical_maximum>29576</logical_maximum>
      <physical_maximum>29576</physical_maximum>
      <unit>
        <si_linear>
          <centimeter/>
        </si_linear>
      </unit>
      <unit_exponent>13</unit_exponent>
      <report_size>16</report_size>
      <report_count>1</report_count>
      <input>
        <variable/>
      </input>
      <usage>desktop_y<!-- Y (31h, dynamic value) --></usage>
      <logical_maximum>16724</logical_maximum>
      <physical_maximum>16724</physical_maximum>
      <input>
        <variable/>
      </input>
      <physical_maximum>0</physical_maximum>
      <unit>
        <none/>
      </unit>
      <unit_exponent>0</unit_exponent>
      <usage_page>digitizer<!-- Digitizer (0Dh) --></usage_page>
      <usage>digitizer_tip_pressure<!-- Tip pressure (30h, dynamic value) --></usage>
      <logical_maximum>1023</logical_maximum>
      <report_size>16</report_size>
      <input>
        <variable/>
      </input>
    </COLLECTION>
  </COLLECTION>
  <usage_page>FF09<!-- FF09h, vendor-defined --></usage_page>
  <usage>13</usage>
  <COLLECTION type="application">
    <report_id>11</report_id>
    <COLLECTION type="physical">
      <logical_minimum>0</logical_minimum>
      <logical_maximum>255</logical_maximum>
      <usage>0</usage>
      <report_size>8</report_size>
      <report_count>7</report_count>
      <input>
        <variable/>
      </input>
    </COLLECTION>
    <usage>0</usage>
    <report_count>3</report_count>
    <feature>
      <variable/>
      <non_linear/>
    </feature>
    <report_id>5</report_id>
    <usage>0</usage>
    <report_count>8</report_count>
    <feature>
      <variable/>
      <non_linear/>
    </feature>
  </COLLECTION>
</descriptor>
